tensorcontainer/__init__.py
tensorcontainer/tensor_annotated.py
tensorcontainer/tensor_container.py
tensorcontainer/tensor_dataclass.py
tensorcontainer/tensor_dict.py
tensorcontainer/types.py
tensorcontainer/utils.py
tensorcontainer/distributions/__init__.py
tensorcontainer/distributions/sampling.py
tensorcontainer/distributions/soft_bernoulli.py
tensorcontainer/distributions/symlog.py
tensorcontainer/distributions/truncated_normal.py
tensorcontainer/tensor_distribution/__init__.py
tensorcontainer/tensor_distribution/base.py
tensorcontainer/tensor_distribution/bernoulli.py
tensorcontainer/tensor_distribution/beta.py
tensorcontainer/tensor_distribution/binomial.py
tensorcontainer/tensor_distribution/categorical.py
tensorcontainer/tensor_distribution/cauchy.py
tensorcontainer/tensor_distribution/chi2.py
tensorcontainer/tensor_distribution/continuous_bernoulli.py
tensorcontainer/tensor_distribution/dirichlet.py
tensorcontainer/tensor_distribution/exponential.py
tensorcontainer/tensor_distribution/fisher_snedecor.py
tensorcontainer/tensor_distribution/gamma.py
tensorcontainer/tensor_distribution/geometric.py
tensorcontainer/tensor_distribution/gumbel.py
tensorcontainer/tensor_distribution/half_cauchy.py
tensorcontainer/tensor_distribution/half_normal.py
tensorcontainer/tensor_distribution/independent.py
tensorcontainer/tensor_distribution/inverse_gamma.py
tensorcontainer/tensor_distribution/kumaraswamy.py
tensorcontainer/tensor_distribution/laplace.py
tensorcontainer/tensor_distribution/lkj_cholesky.py
tensorcontainer/tensor_distribution/log_normal.py
tensorcontainer/tensor_distribution/logistic_normal.py
tensorcontainer/tensor_distribution/low_rank_multivariate_normal.py
tensorcontainer/tensor_distribution/mixture_same_family.py
tensorcontainer/tensor_distribution/multinomial.py
tensorcontainer/tensor_distribution/multivariate_normal.py
tensorcontainer/tensor_distribution/negative_binomial.py
tensorcontainer/tensor_distribution/normal.py
tensorcontainer-0.8.2.dist-info/METADATA
tensorcontainer-0.8.2.dist-info/WHEEL
tensorcontainer-0.8.2.dist-info/top_level.txt
tensorcontainer-0.8.2.dist-info/RECORD
