Metadata-Version: 2.4
Name: tensorcontainer
Version: 0.8.2
Summary: TensorDict-like functionality for PyTorch with PyTree compatibility and torch.compile support
Author-email: Tim Joseph <tim@mctigger.com>
License: MIT
Project-URL: Homepage, https://github.com/mctigger/tensor-container
Keywords: deep learning,tensordict,pytorch
Classifier: License :: OSI Approved :: MIT License
Classifier: Programming Language :: Python :: 3
Classifier: Programming Language :: Python :: 3.9
Classifier: Programming Language :: Python :: 3.10
Classifier: Programming Language :: Python :: 3.11
Classifier: Programming Language :: Python :: 3.12
Classifier: Development Status :: 4 - Beta
Classifier: Topic :: Scientific/Engineering :: Artificial Intelligence
Classifier: Topic :: Software Development :: Libraries :: Python Modules
Classifier: Intended Audience :: Science/Research
Classifier: Intended Audience :: Developers
Requires-Python: >=3.9
Requires-Dist: torch>=2.6
Provides-Extra: dev
Requires-Dist: pytest<8.0,>=7.2; extra == "dev"
Requires-Dist: pytest-cov; extra == "dev"
Requires-Dist: ruff; extra == "dev"
